{
  "swagger": "2.0",
  "info": {
    "title": "My API",
    "description": "Description",
    "version": "1.0.0"
  },
  "host": "localhost:3000",
  "basePath": "/",
  "schemes": [
    "http"
  ],
  "paths": {
    "/contacts/": {
      "get": {
        "tags": [
          "Contacts"
        ],
        "summary": "Get all contacts",
        "description": "This request gets all contacts in the database",
        "produces": [
          "application/json"
        ],
        "parameters": [],
        "responses": {
          "200": {
            "description": "OK"
          }
        }
      },
      "post": {
        "tags": [
          "Contacts"
        ],
        "summary": "Create a contact",
        "description": "This request creates a new contact",
        "parameters": [
          {
            "name": "contact",
            "in": "body",
            "description": "Contact object",
            "required": true,
            "schema": {
              "type": "object",
              "properties": {
                "firstname": {
                  "type": "string",
                  "example": "John"
                },
                "lastname": {
                  "type": "string",
                  "example": "Doe"
                },
                "email": {
                  "type": "string",
                  "example": "johndoe@email.com"
                },
                "favoriteColor": {
                  "type": "string",
                  "example": "blue"
                },
                "birthday": {
                  "type": "string",
                  "example": "1996-03-12T12:00:00.000Z"
                }
              },
              "required": [
                "firstname",
                "lastname",
                "email",
                "favoriteColor",
                "birthday"
              ]
            }
          }
        ],
        "responses": {
          "200": {
            "description": "OK"
          },
          "500": {
            "description": "Internal Server Error"
          }
        }
      }
    },
    "/contacts/{id}": {
      "get": {
        "tags": [
          "Contacts"
        ],
        "summary": "Get contact by id",
        "description": "This request gets an individual contact by id number",
        "produces": [
          "application/json"
        ],
        "parameters": [
          {
            "name": "id",
            "in": "path",
            "required": true,
            "type": "string",
            "description": "Contact id"
          }
        ],
        "responses": {
          "200": {
            "description": "OK"
          }
        }
      },
      "put": {
        "tags": [
          "Contacts"
        ],
        "summary": "Update contact by Id",
        "description": "This is a request to update a given contact record",
        "parameters": [
          {
            "name": "id",
            "in": "path",
            "required": true,
            "type": "string",
            "description": "Contact ID."
          },
          {
            "name": "contact",
            "in": "body",
            "description": "Contact object",
            "required": true,
            "schema": {
              "type": "object",
              "properties": {
                "firstname": {
                  "type": "string",
                  "example": "John"
                },
                "lastname": {
                  "type": "string",
                  "example": "Doe"
                },
                "email": {
                  "type": "string",
                  "example": "johndoe@email.com"
                },
                "favoriteColor": {
                  "type": "string",
                  "example": "blue"
                },
                "birthday": {
                  "type": "string",
                  "example": "1996-03-12T12:00:00.000Z"
                }
              }
            }
          }
        ],
        "responses": {
          "200": {
            "description": "OK"
          },
          "501": {
            "description": "Not Implemented"
          }
        }
      },
      "delete": {
        "tags": [
          "Contacts"
        ],
        "summary": "Deletes a given contact",
        "description": "This request deletes a given contact record",
        "parameters": [
          {
            "name": "id",
            "in": "path",
            "required": true,
            "type": "string",
            "description": "Contact id"
          }
        ],
        "responses": {
          "202": {
            "description": "Accepted"
          },
          "502": {
            "description": "Bad Gateway"
          }
        }
      }
    }
  }
}